odoo/addons/delivery_carrier_account/README.rst
odoo/addons/delivery_carrier_account/__init__.py
odoo/addons/delivery_carrier_account/__manifest__.py
odoo/addons/delivery_carrier_account/i18n/delivery_carrier_account.pot
odoo/addons/delivery_carrier_account/i18n/es.po
odoo/addons/delivery_carrier_account/i18n/it.po
odoo/addons/delivery_carrier_account/models/__init__.py
odoo/addons/delivery_carrier_account/models/carrier_account.py
odoo/addons/delivery_carrier_account/models/delivery_carrier.py
odoo/addons/delivery_carrier_account/models/stock_picking.py
odoo/addons/delivery_carrier_account/readme/CONTRIBUTORS.md
odoo/addons/delivery_carrier_account/readme/DESCRIPTION.md
odoo/addons/delivery_carrier_account/security/carrier_security.xml
odoo/addons/delivery_carrier_account/security/ir.model.access.csv
odoo/addons/delivery_carrier_account/static/description/icon.png
odoo/addons/delivery_carrier_account/static/description/index.html
odoo/addons/delivery_carrier_account/tests/__init__.py
odoo/addons/delivery_carrier_account/tests/test_carrier_account.py
odoo/addons/delivery_carrier_account/views/carrier_account.xml
odoo/addons/delivery_carrier_account/views/delivery_carrier.xml
odoo_addon_delivery_carrier_account-19.0.1.0.0.2.dist-info/METADATA
odoo_addon_delivery_carrier_account-19.0.1.0.0.2.dist-info/WHEEL
odoo_addon_delivery_carrier_account-19.0.1.0.0.2.dist-info/top_level.txt
odoo_addon_delivery_carrier_account-19.0.1.0.0.2.dist-info/RECORD
